{
    "paths": [
        {
            "name": "/party",
            "lambdaFunction": "djmelamda",
            "privacy": {
                "private": true,
                "auth": [
                    "/POST",
                    "/GET",
                    "/PUT",
                    "/PATCH",
                    "/DELETE"
                ]
            }
        },
        {
            "name": "/test",
            "lambdaFunction": "test",
            "privacy": {
                "private": true,
                "auth": [
                    "/POST",
                    "/GET"
                ]
            }
        }
    ],
    "resourceName": "djmeapi",
    "apiName": "djmeapi",
    "functionArns": [
        {
            "lambdaFunction": "djmelamda"
        },
        {
            "lambdaFunction": "test"
        }
    ],
    "privacy": {
        "auth": 2,
        "unauth": 0,
        "authRoleName": "djmeserver-20190414144000-authRole",
        "unAuthRoleName": "djmeserver-20190414144000-unauthRole"
    },
    "dependsOn": [
        {
            "category": "function",
            "resourceName": "djmelamda",
            "attributes": [
                "Name",
                "Arn"
            ]
        },
        {
            "category": "function",
            "resourceName": "test",
            "attributes": [
                "Name",
                "Arn"
            ]
        }
    ]
}